{
  "project_info": {
    "project_number": "221247537307",
    "project_id": "flutter-chat-messenger-d7ce5",
    "storage_bucket": "flutter-chat-messenger-d7ce5.appspot.com"
  },
  "client": [
    {
      "client_info": {
        "mobilesdk_app_id": "1:221247537307:android:884ac94ea0a7641885063e",
        "android_client_info": {
          "package_name": "com.example.chat_firebase"
        }
      },
      "oauth_client": [],
      "api_key": [
        {
          "current_key": "AIzaSyAeQNvG5ZhfZKiur2lc5agN32Hi_Pv7BiE"
        }
      ],
      "services": {
        "appinvite_service": {
          "other_platform_oauth_client": []
        }
      }
    }
  ],
  "configuration_version": "1"
}